opentf/agent/__init__.py
opentf/agent/agent.py
opentf_agent-1.7.0.dist-info/LICENSE
opentf_agent-1.7.0.dist-info/METADATA
opentf_agent-1.7.0.dist-info/WHEEL
opentf_agent-1.7.0.dist-info/entry_points.txt
opentf_agent-1.7.0.dist-info/top_level.txt
opentf_agent-1.7.0.dist-info/RECORD
